README.md
setup.cfg
setup.py
conversao_temperatura/__init__.py
conversao_temperatura/conversao_temperatura.py
conversao_temperatura.egg-info/PKG-INFO
conversao_temperatura.egg-info/SOURCES.txt
conversao_temperatura.egg-info/dependency_links.txt
conversao_temperatura.egg-info/top_level.txt