Metadata-Version: 1.1
Name: conversao-temperatura
Version: 1.0.0
Summary: Um simples conversor de temperatura (Celsius - Fahrenheit)
Home-page: https://github.com/FAntoniasse/Conversao_temperatura
Author: Fabrício Antoniasse
Author-email: fabricio.antoniasse@hotmail.com
License: MIT
Project-URL: Código fonte, https://github.com/FAntoniasse/Conversao_temperatura
Project-URL: Download, https://github.com/FAntoniasse/Conversao_temperatura/blob/main/conversor.rar
Keywords: conversor temperatura
Platform: UNKNOWN
Classifier: Development Status :: 5 - Production/Stable
Classifier: Intended Audience :: Developers
Classifier: License :: OSI Approved :: MIT License
Classifier: Natural Language :: Portuguese (Brazilian)
Classifier: Operating System :: OS Independent
Classifier: Topic :: Software Development :: Internationalization
Classifier: Topic :: Scientific/Engineering :: Physics
